[
  {
    "1": "O nome Olinda foi dado a partir de uma frase dita por: ",
    "2": "Complete as informações abaixo:\n\n Fundada em ____, Olinda foi elevada à vila em ____ e foi a capital da Capitania de Pernambuco até ____. A cidade prosperou com o extrativismo do pau-brasil e o cultivo da cana-de-açúcar, tornando-se um dos mais importantes centros comerciais da colônia.",
    "3": "Qual igreja foi destruída por um incêndio provocado pelos holandeses em 1631?",
    "4": "A Biblioteca Pública de Olinda é a a primeira do Estado de Pernambuco e a 3ª a ser estabelecida no Brasil. Quem concebeu a Biblioteca Pública de Olinda através de um decreto em Dezembro de 1830?",
    "5": "Onde está localizado o primeiro convento xxx?",
    "6": "Em que rua aconteceu xxx?",
    "7": "Onde aconteceu a guerra dos...?",
    "8": "Quantas pessoas morreram...?",
    "9": "O mourisco fica localizado em?",
    "10": "Em que ano aconteceu...?"
  },
  {
    "1": {
      "a": "Duarte Coelho",
      "b": "João de Barros",
      "c": "Pedro Lopes de Souza",
      "d": "Martin Afonso"
    },
    "2": {
      "a": "1537, 1558 e 1554, respectivamente",
      "b": "1536, 1539 e 1601, respectivamente",
      "c": "1535, 1537 e 1654, respectivamente",
      "d": "1534, 1538 e 1664, respectivamente"
    },
    "3": {
      "a": "Igreja da Sé",
      "b": "Igreja do Carmo",
      "c": "Igreja do Amparo",
      "d": "Igreja da Misericórdia"
    },
    "4": {
      "a": "Dom Pedro I",
      "b": "Dom Pedro II",
      "c": "Cristovão Colombo",
      "d": "Pedro Alvares Cabral"
    },
    "5": {
      "a": "opção 1",
      "b": "opção 2",
      "c": "opção 3",
      "d": "opção 4"
    },
    "6": {
      "a": "opção 1",
      "b": "opção 2",
      "c": "opção 3",
      "d": "opção 4"
    },
    "7": {
      "a": "opção 1",
      "b": "opção 2",
      "c": "opção 3",
      "d": "opção 4"
    },
    "8": {
      "a": "opção 1",
      "b": "opção 2",
      "c": "opção 3",
      "d": "opção 4"
    },
    "9": {
      "a": "opção 1",
      "b": "opção 2",
      "c": "opção 3",
      "d": "opção 4"
    },
    "10": {
      "a": "opção 1",
      "b": "opção 2",
      "c": "opção 3",
      "d": "opção 4"
    }
  },
  {
    "1": "Duarte Coelho",
    "2": "1535, 1537 e 1654, respectivamente",
    "3": "Igreja do Amparo",
    "4": "Dom Pedro I",
    "5": "opção 3",
    "6": "opção 2",
    "7": "opção 2",
    "8": "opção 4",
    "9": "opção 3",
    "10": "opção 3"
  }
]